[
  {
    "code": "leather_cap_recipe",
    "name": "Casque en cuir",
    "result_item_code": "leather_cap",
    "result_quantity": 1,
    "ingredients": [
      { "item_code": "leather_strip", "quantity": 3 },
      { "item_code": "linen_cloth", "quantity": 1 }
    ]
  },
  {
    "code": "leather_chest_recipe",
    "name": "Plastron en cuir",
    "result_item_code": "leather_chest",
    "result_quantity": 1,
    "ingredients": [
      { "item_code": "leather_strip", "quantity": 5 },
      { "item_code": "linen_cloth", "quantity": 2 }
    ]
  },
  {
    "code": "leather_legs_recipe",
    "name": "Jambières en cuir",
    "result_item_code": "leather_legs",
    "result_quantity": 1,
    "ingredients": [
      { "item_code": "leather_strip", "quantity": 4 },
      { "item_code": "linen_cloth", "quantity": 2 }
    ]
  },
  {
    "code": "leather_boots_recipe",
    "name": "Bottes en cuir",
    "result_item_code": "leather_boots",
    "result_quantity": 1,
    "ingredients": [
      { "item_code": "leather_strip", "quantity": 3 }
    ]
  },
  {
    "code": "leather_belt_recipe",
    "name": "Ceinture en cuir",
    "result_item_code": "leather_belt",
    "result_quantity": 1,
    "ingredients": [
      { "item_code": "leather_strip", "quantity": 2 },
      { "item_code": "iron_ingot", "quantity": 1 }
    ]
  },
  {
    "code": "leather_bracelet_recipe",
    "name": "Bracelet en cuir",
    "result_item_code": "leather_bracelet",
    "result_quantity": 1,
    "ingredients": [
      { "item_code": "leather_strip", "quantity": 2 }
    ]
  },
  {
    "code": "linen_cape_recipe",
    "name": "Cape en lin",
    "result_item_code": "linen_cape",
    "result_quantity": 1,
    "ingredients": [
      { "item_code": "linen_cloth", "quantity": 4 },
      { "item_code": "leather_strip", "quantity": 1 }
    ]
  },
  {
    "code": "stone_earring_recipe",
    "name": "Boucle de pierre polie",
    "result_item_code": "stone_earring",
    "result_quantity": 1,
    "ingredients": [
      { "item_code": "polished_stone", "quantity": 2 },
      { "item_code": "iron_ingot", "quantity": 1 }
    ]
  },

  {
    "code": "wood_sword_recipe",
    "name": "Épée en bois",
    "result_item_code": "wood_sword",
    "result_quantity": 1,
    "ingredients": [
      { "item_code": "wood_log", "quantity": 3 }
    ]
  },
  {
    "code": "wooden_shield_recipe",
    "name": "Bouclier en bois",
    "result_item_code": "wooden_shield",
    "result_quantity": 1,
    "ingredients": [
      { "item_code": "wood_log", "quantity": 4 },
      { "item_code": "leather_strip", "quantity": 1 }
    ]
  },
  {
    "code": "iron_buckler_recipe",
    "name": "Rondache en fer",
    "result_item_code": "iron_buckler",
    "result_quantity": 1,
    "ingredients": [
      { "item_code": "iron_ingot", "quantity": 3 },
      { "item_code": "leather_strip", "quantity": 1 }
    ]
  },
  {
    "code": "slime_blade_recipe",
    "name": "Lame visqueuse",
    "result_item_code": "slime_blade",
    "result_quantity": 1,
    "ingredients": [
      { "item_code": "slime_gel", "quantity": 3 },
      { "item_code": "wood_sword", "quantity": 1 }
    ]
  },
  {
    "code": "hunter_dagger_recipe",
    "name": "Dague du chasseur",
    "result_item_code": "hunter_dagger",
    "result_quantity": 1,
    "ingredients": [
      { "item_code": "iron_ingot", "quantity": 2 },
      { "item_code": "leather_strip", "quantity": 1 }
    ]
  },
  {
    "code": "gobelin_axe_recipe",
    "name": "Hache gobeline",
    "result_item_code": "gobelin_axe",
    "result_quantity": 1,
    "ingredients": [
      { "item_code": "gobelin_tooth", "quantity": 4 },
      { "item_code": "iron_ingot", "quantity": 2 },
      { "item_code": "wood_log", "quantity": 1 }
    ]
  },
  {
    "code": "iron_helmet_recipe",
    "name": "Casque de fer",
    "result_item_code": "iron_helmet",
    "result_quantity": 1,
    "ingredients": [
      { "item_code": "iron_ingot", "quantity": 4 },
      { "item_code": "leather_strip", "quantity": 1 }
    ]
  },
  {
    "code": "iron_chest_recipe",
    "name": "Plastron de fer",
    "result_item_code": "iron_chest",
    "result_quantity": 1,
    "ingredients": [
      { "item_code": "iron_ingot", "quantity": 6 },
      { "item_code": "leather_strip", "quantity": 2 }
    ]
  },
  {
    "code": "iron_legs_recipe",
    "name": "Jambières de fer",
    "result_item_code": "iron_legs",
    "result_quantity": 1,
    "ingredients": [
      { "item_code": "iron_ingot", "quantity": 5 },
      { "item_code": "leather_strip", "quantity": 2 }
    ]
  },
  {
    "code": "iron_boots_recipe",
    "name": "Bottes en fer",
    "result_item_code": "iron_boots",
    "result_quantity": 1,
    "ingredients": [
      { "item_code": "iron_ingot", "quantity": 4 },
      { "item_code": "leather_strip", "quantity": 1 }
    ]
  },
  {
    "code": "gobelin_crown_recipe",
    "name": "Couronne gobeline",
    "result_item_code": "gobelin_crown",
    "result_quantity": 1,
    "ingredients": [
      { "item_code": "gobelin_tooth", "quantity": 6 },
      { "item_code": "polished_stone", "quantity": 2 },
      { "item_code": "iron_ingot", "quantity": 1 }
    ]
  },

  {
    "code": "iron_ring_recipe",
    "name": "Anneau de fer",
    "result_item_code": "iron_ring",
    "result_quantity": 1,
    "ingredients": [
      { "item_code": "iron_ingot", "quantity": 2 }
    ]
  },
  {
    "code": "gobelin_ring_recipe",
    "name": "Bague gobeline",
    "result_item_code": "gobelin_ring",
    "result_quantity": 1,
    "ingredients": [
      { "item_code": "gobelin_tooth", "quantity": 3 },
      { "item_code": "iron_ingot", "quantity": 1 },
      { "item_code": "polished_stone", "quantity": 1 }
    ]
  },
  {
    "code": "slime_pendant_recipe",
    "name": "Pendentif de Slime",
    "result_item_code": "slime_pendant",
    "result_quantity": 1,
    "ingredients": [
      { "item_code": "slime_gel", "quantity": 5 },
      { "item_code": "polished_stone", "quantity": 1 },
      { "item_code": "leather_strip", "quantity": 1 }
    ]
  },

  {
    "code": "linen_hood_recipe",
    "name": "Capuche en lin",
    "result_item_code": "linen_hood",
    "result_quantity": 1,
    "ingredients": [
      { "item_code": "linen_cloth", "quantity": 4 },
      { "item_code": "leather_strip", "quantity": 1 }
    ]
  },
  {
    "code": "linen_robe_recipe",
    "name": "Robe en lin",
    "result_item_code": "linen_robe",
    "result_quantity": 1,
    "ingredients": [
      { "item_code": "linen_cloth", "quantity": 6 },
      { "item_code": "leather_strip", "quantity": 1 }
    ]
  },
  {
    "code": "linen_gloves_recipe",
    "name": "Mitaines en lin",
    "result_item_code": "linen_gloves",
    "result_quantity": 1,
    "ingredients": [
      { "item_code": "linen_cloth", "quantity": 3 }
    ]
  },
  {
    "code": "slime_cloak_recipe",
    "name": "Cape gluante",
    "result_item_code": "slime_cloak",
    "result_quantity": 1,
    "ingredients": [
      { "item_code": "slime_gel", "quantity": 5 },
      { "item_code": "linen_cloth", "quantity": 3 },
      { "item_code": "leather_strip", "quantity": 1 }
    ]
  },
  {
    "code": "goblin_amulet_recipe",
    "name": "Amulette gobeline",
    "result_item_code": "goblin_amulet",
    "result_quantity": 1,
    "ingredients": [
      { "item_code": "gobelin_tooth", "quantity": 5 },
      { "item_code": "polished_stone", "quantity": 2 },
      { "item_code": "leather_strip", "quantity": 1 }
    ]
  },
  {
    "code": "polished_stone_ring_recipe",
    "name": "Anneau de pierre polie",
    "result_item_code": "polished_stone_ring",
    "result_quantity": 1,
    "ingredients": [
      { "item_code": "polished_stone", "quantity": 3 }
    ]
  },
  {
    "code": "iron_gauntlets_recipe",
    "name": "Gantelets en fer",
    "result_item_code": "iron_gauntlets",
    "result_quantity": 1,
    "ingredients": [
      { "item_code": "iron_ingot", "quantity": 4 },
      { "item_code": "leather_strip", "quantity": 2 }
    ]
  },

  {
    "code": "iron_dagger_recipe",
    "name": "Dague en fer",
    "result_item_code": "iron_dagger",
    "result_quantity": 1,
    "ingredients": [
      { "item_code": "iron_ingot", "quantity": 2 },
      { "item_code": "wood_log", "quantity": 1 },
      { "item_code": "leather_strip", "quantity": 1 }
    ]
  },
  {
    "code": "goblin_blade_recipe",
    "name": "Lame gobeline",
    "result_item_code": "goblin_blade",
    "result_quantity": 1,
    "ingredients": [
      { "item_code": "gobelin_tooth", "quantity": 4 },
      { "item_code": "iron_ingot", "quantity": 2 },
      { "item_code": "wood_log", "quantity": 1 }
    ]
  },
  {
    "code": "slime_shield_recipe",
    "name": "Bouclier visqueux",
    "result_item_code": "slime_shield",
    "result_quantity": 1,
    "ingredients": [
      { "item_code": "slime_gel", "quantity": 4 },
      { "item_code": "wood_log", "quantity": 3 },
      { "item_code": "leather_strip", "quantity": 1 }
    ]
  },
  {
    "code": "gobelin_plastron_recipe",
    "name": "Plastron gobelin",
    "result_item_code": "gobelin_plastron",
    "result_quantity": 1,
    "ingredients": [
      { "item_code": "gobelin_tooth", "quantity": 5 },
      { "item_code": "iron_ingot", "quantity": 2 },
      { "item_code": "leather_strip", "quantity": 1 }
    ]
  },
  {
    "code": "gobelin_jambieres_recipe",
    "name": "Jambières gobelin",
    "result_item_code": "gobelin_jambieres",
    "result_quantity": 1,
    "ingredients": [
      { "item_code": "gobelin_tooth", "quantity": 4 },
      { "item_code": "iron_ingot", "quantity": 2 },
      { "item_code": "leather_strip", "quantity": 1 }
    ]
  },
  {
    "code": "gobelin_bottes_recipe",
    "name": "Bottes gobelin",
    "result_item_code": "gobelin_bottes",
    "result_quantity": 1,
    "ingredients": [
      { "item_code": "gobelin_tooth", "quantity": 3 },
      { "item_code": "iron_ingot", "quantity": 1 },
      { "item_code": "leather_strip", "quantity": 1 }
    ]
  },
  {
    "code": "gobelin_main_gauche_recipe",
    "name": "Bouclier gobelin",
    "result_item_code": "gobelin_main_gauche",
    "result_quantity": 1,
    "ingredients": [
      { "item_code": "gobelin_tooth", "quantity": 3 },
      { "item_code": "iron_ingot", "quantity": 1 },
      { "item_code": "wood_log", "quantity": 2 },
      { "item_code": "leather_strip", "quantity": 1 }
    ]
  },
  {
    "code": "gobelin_bracelet_recipe",
    "name": "Bracelet gobelin",
    "result_item_code": "gobelin_bracelet",
    "result_quantity": 1,
    "ingredients": [
      { "item_code": "gobelin_tooth", "quantity": 2 },
      { "item_code": "iron_ingot", "quantity": 1 }
    ]
  },
  {
    "code": "gobelin_ceinture_recipe",
    "name": "Ceinture gobelin",
    "result_item_code": "gobelin_ceinture",
    "result_quantity": 1,
    "ingredients": [
      { "item_code": "gobelin_tooth", "quantity": 2 },
      { "item_code": "iron_ingot", "quantity": 1 },
      { "item_code": "leather_strip", "quantity": 1 }
    ]
  },
  {
    "code": "gobelin_cape_recipe",
    "name": "Cape gobelin",
    "result_item_code": "gobelin_cape",
    "result_quantity": 1,
    "ingredients": [
      { "item_code": "gobelin_tooth", "quantity": 4 },
      { "item_code": "linen_cloth", "quantity": 2 },
      { "item_code": "leather_strip", "quantity": 1 }
    ]
  },
  {
    "code": "gobelin_boucle_oreille_recipe",
    "name": "Boucle gobelin",
    "result_item_code": "gobelin_boucle_oreille",
    "result_quantity": 1,
    "ingredients": [
      { "item_code": "gobelin_tooth", "quantity": 2 },
      { "item_code": "polished_stone", "quantity": 1 }
    ]
  },
  {
    "code": "iron_collier_recipe",
    "name": "Collier en fer",
    "result_item_code": "iron_collier",
    "result_quantity": 1,
    "ingredients": [
      { "item_code": "iron_ingot", "quantity": 4 },
      { "item_code": "polished_stone", "quantity": 1 },
      { "item_code": "leather_strip", "quantity": 1 }
    ]
  },
  {
    "code": "iron_ceinture_recipe",
    "name": "Ceinture en fer",
    "result_item_code": "iron_ceinture",
    "result_quantity": 1,
    "ingredients": [
      { "item_code": "iron_ingot", "quantity": 2 },
      { "item_code": "leather_strip", "quantity": 1 }
    ]
  },
  {
    "code": "iron_cape_recipe",
    "name": "Cape en fer",
    "result_item_code": "iron_cape",
    "result_quantity": 1,
    "ingredients": [
      { "item_code": "iron_ingot", "quantity": 4 },
      { "item_code": "linen_cloth", "quantity": 2 },
      { "item_code": "leather_strip", "quantity": 1 }
    ]
  },
  {
    "code": "iron_boucle_oreille_recipe",
    "name": "Boucle en fer",
    "result_item_code": "iron_boucle_oreille",
    "result_quantity": 1,
    "ingredients": [
      { "item_code": "iron_ingot", "quantity": 2 },
      { "item_code": "polished_stone", "quantity": 1 }
    ]
  },
  {
    "code": "leather_main_droite_recipe",
    "name": "Lame en cuir",
    "result_item_code": "leather_main_droite",
    "result_quantity": 1,
    "ingredients": [
      { "item_code": "leather_strip", "quantity": 3 },
      { "item_code": "wood_log", "quantity": 2 },
      { "item_code": "iron_ingot", "quantity": 1 }
    ]
  },
  {
    "code": "leather_main_gauche_recipe",
    "name": "Bouclier en cuir",
    "result_item_code": "leather_main_gauche",
    "result_quantity": 1,
    "ingredients": [
      { "item_code": "leather_strip", "quantity": 3 },
      { "item_code": "wood_log", "quantity": 3 },
      { "item_code": "iron_ingot", "quantity": 1 }
    ]
  },
  {
    "code": "leather_collier_recipe",
    "name": "Collier en cuir",
    "result_item_code": "leather_collier",
    "result_quantity": 1,
    "ingredients": [
      { "item_code": "leather_strip", "quantity": 4 },
      { "item_code": "polished_stone", "quantity": 1 },
      { "item_code": "linen_cloth", "quantity": 1 }
    ]
  },
  {
    "code": "leather_bague_recipe",
    "name": "Bague en cuir",
    "result_item_code": "leather_bague",
    "result_quantity": 1,
    "ingredients": [
      { "item_code": "leather_strip", "quantity": 2 },
      { "item_code": "polished_stone", "quantity": 1 }
    ]
  },
  {
    "code": "leather_cape_recipe",
    "name": "Cape en cuir",
    "result_item_code": "leather_cape",
    "result_quantity": 1,
    "ingredients": [
      { "item_code": "leather_strip", "quantity": 5 },
      { "item_code": "linen_cloth", "quantity": 2 }
    ]
  },
  {
    "code": "leather_boucle_oreille_recipe",
    "name": "Boucle en cuir",
    "result_item_code": "leather_boucle_oreille",
    "result_quantity": 1,
    "ingredients": [
      { "item_code": "leather_strip", "quantity": 2 },
      { "item_code": "polished_stone", "quantity": 1 }
    ]
  },
  {
    "code": "linen_jambieres_recipe",
    "name": "Jambières en lin",
    "result_item_code": "linen_jambieres",
    "result_quantity": 1,
    "ingredients": [
      { "item_code": "linen_cloth", "quantity": 4 },
      { "item_code": "leather_strip", "quantity": 2 }
    ]
  },
  {
    "code": "linen_bottes_recipe",
    "name": "Bottes en lin",
    "result_item_code": "linen_bottes",
    "result_quantity": 1,
    "ingredients": [
      { "item_code": "linen_cloth", "quantity": 3 },
      { "item_code": "leather_strip", "quantity": 1 }
    ]
  },
  {
    "code": "linen_main_droite_recipe",
    "name": "Lame en lin",
    "result_item_code": "linen_main_droite",
    "result_quantity": 1,
    "ingredients": [
      { "item_code": "linen_cloth", "quantity": 3 },
      { "item_code": "wood_log", "quantity": 2 },
      { "item_code": "iron_ingot", "quantity": 1 }
    ]
  },
  {
    "code": "linen_main_gauche_recipe",
    "name": "Bouclier en lin",
    "result_item_code": "linen_main_gauche",
    "result_quantity": 1,
    "ingredients": [
      { "item_code": "linen_cloth", "quantity": 3 },
      { "item_code": "wood_log", "quantity": 3 },
      { "item_code": "leather_strip", "quantity": 1 }
    ]
  },
  {
    "code": "linen_collier_recipe",
    "name": "Collier en lin",
    "result_item_code": "linen_collier",
    "result_quantity": 1,
    "ingredients": [
      { "item_code": "linen_cloth", "quantity": 4 },
      { "item_code": "polished_stone", "quantity": 1 },
      { "item_code": "leather_strip", "quantity": 1 }
    ]
  },
  {
    "code": "linen_bague_recipe",
    "name": "Bague en lin",
    "result_item_code": "linen_bague",
    "result_quantity": 1,
    "ingredients": [
      { "item_code": "linen_cloth", "quantity": 2 },
      { "item_code": "polished_stone", "quantity": 1 }
    ]
  },
  {
    "code": "linen_ceinture_recipe",
    "name": "Ceinture en lin",
    "result_item_code": "linen_ceinture",
    "result_quantity": 1,
    "ingredients": [
      { "item_code": "linen_cloth", "quantity": 2 },
      { "item_code": "iron_ingot", "quantity": 1 }
    ]
  },
  {
    "code": "linen_boucle_oreille_recipe",
    "name": "Boucle en lin",
    "result_item_code": "linen_boucle_oreille",
    "result_quantity": 1,
    "ingredients": [
      { "item_code": "linen_cloth", "quantity": 2 },
      { "item_code": "polished_stone", "quantity": 1 }
    ]
  },
  {
    "code": "slime_casque_recipe",
    "name": "Casque de slime",
    "result_item_code": "slime_casque",
    "result_quantity": 1,
    "ingredients": [
      { "item_code": "slime_gel", "quantity": 4 },
      { "item_code": "leather_strip", "quantity": 1 }
    ]
  },
  {
    "code": "slime_plastron_recipe",
    "name": "Plastron de slime",
    "result_item_code": "slime_plastron",
    "result_quantity": 1,
    "ingredients": [
      { "item_code": "slime_gel", "quantity": 5 },
      { "item_code": "leather_strip", "quantity": 2 }
    ]
  },
  {
    "code": "slime_jambieres_recipe",
    "name": "Jambières de slime",
    "result_item_code": "slime_jambieres",
    "result_quantity": 1,
    "ingredients": [
      { "item_code": "slime_gel", "quantity": 4 },
      { "item_code": "leather_strip", "quantity": 2 }
    ]
  },
  {
    "code": "slime_bottes_recipe",
    "name": "Bottes de slime",
    "result_item_code": "slime_bottes",
    "result_quantity": 1,
    "ingredients": [
      { "item_code": "slime_gel", "quantity": 3 },
      { "item_code": "leather_strip", "quantity": 1 }
    ]
  },
  {
    "code": "slime_bracelet_recipe",
    "name": "Bracelet de slime",
    "result_item_code": "slime_bracelet",
    "result_quantity": 1,
    "ingredients": [
      { "item_code": "slime_gel", "quantity": 2 },
      { "item_code": "iron_ingot", "quantity": 1 }
    ]
  },
  {
    "code": "slime_bague_recipe",
    "name": "Bague de slime",
    "result_item_code": "slime_bague",
    "result_quantity": 1,
    "ingredients": [
      { "item_code": "slime_gel", "quantity": 2 },
      { "item_code": "polished_stone", "quantity": 1 }
    ]
  },
  {
    "code": "slime_ceinture_recipe",
    "name": "Ceinture de slime",
    "result_item_code": "slime_ceinture",
    "result_quantity": 1,
    "ingredients": [
      { "item_code": "slime_gel", "quantity": 2 },
      { "item_code": "leather_strip", "quantity": 1 }
    ]
  },
  {
    "code": "slime_boucle_oreille_recipe",
    "name": "Boucle de slime",
    "result_item_code": "slime_boucle_oreille",
    "result_quantity": 1,
    "ingredients": [
      { "item_code": "slime_gel", "quantity": 2 },
      { "item_code": "polished_stone", "quantity": 1 }
    ]
  },
  {
    "code": "iron_sword_recipe",
    "name": "Épée en fer",
    "result_item_code": "iron_sword",
    "result_quantity": 1,
    "ingredients": [
      { "item_code": "iron_ingot", "quantity": 3 },
      { "item_code": "wood_log", "quantity": 1 },
      { "item_code": "leather_strip", "quantity": 1 }
    ]
  },
  {
    "code": "iron_warshield_recipe",
    "name": "Pavois en fer",
    "result_item_code": "iron_warshield",
    "result_quantity": 1,
    "ingredients": [
      { "item_code": "iron_ingot", "quantity": 4 },
      { "item_code": "leather_strip", "quantity": 2 }
    ]
  },
  {
    "code": "iron_greatsword_recipe",
    "name": "Espadon en fer",
    "result_item_code": "iron_greatsword",
    "result_quantity": 1,
    "ingredients": [
      { "item_code": "iron_ingot", "quantity": 6 },
      { "item_code": "wood_log", "quantity": 3 },
      { "item_code": "leather_strip", "quantity": 3 }
    ]
  },
  {
    "code": "iron_tower_shield_recipe",
    "name": "Tour en fer",
    "result_item_code": "iron_tower_shield",
    "result_quantity": 1,
    "ingredients": [
      { "item_code": "iron_ingot", "quantity": 9 },
      { "item_code": "leather_strip", "quantity": 3 }
    ]
  },
  {
    "code": "slime_morningstar_recipe",
    "name": "Morningstar visqueuse",
    "result_item_code": "slime_morningstar",
    "result_quantity": 1,
    "ingredients": [
      { "item_code": "slime_gel", "quantity": 3 },
      { "item_code": "wood_log", "quantity": 2 }
    ]
  },
  {
    "code": "slime_buckler_recipe",
    "name": "Bouclier de gel",
    "result_item_code": "slime_buckler",
    "result_quantity": 1,
    "ingredients": [
      { "item_code": "slime_gel", "quantity": 3 },
      { "item_code": "wood_log", "quantity": 2 },
      { "item_code": "leather_strip", "quantity": 1 }
    ]
  },
  {
    "code": "slime_greatblade_recipe",
    "name": "Lame visqueuse colossale",
    "result_item_code": "slime_greatblade",
    "result_quantity": 1,
    "ingredients": [
      { "item_code": "slime_gel", "quantity": 9 },
      { "item_code": "wood_log", "quantity": 6 },
      { "item_code": "iron_ingot", "quantity": 3 }
    ]
  },
  {
    "code": "slime_tower_shield_recipe",
    "name": "Tour de gel",
    "result_item_code": "slime_tower_shield",
    "result_quantity": 1,
    "ingredients": [
      { "item_code": "slime_gel", "quantity": 12 },
      { "item_code": "wood_log", "quantity": 9 },
      { "item_code": "leather_strip", "quantity": 3 }
    ]
  },
  {
    "code": "gobelin_buckler_recipe",
    "name": "Rondache gobeline",
    "result_item_code": "gobelin_buckler",
    "result_quantity": 1,
    "ingredients": [
      { "item_code": "gobelin_tooth", "quantity": 3 },
      { "item_code": "iron_ingot", "quantity": 1 },
      { "item_code": "leather_strip", "quantity": 1 }
    ]
  },
  {
    "code": "gobelin_greataxe_recipe",
    "name": "Grande hache gobeline",
    "result_item_code": "gobelin_greataxe",
    "result_quantity": 1,
    "ingredients": [
      { "item_code": "gobelin_tooth", "quantity": 12 },
      { "item_code": "iron_ingot", "quantity": 6 },
      { "item_code": "wood_log", "quantity": 3 }
    ]
  },
  {
    "code": "gobelin_warshield_recipe",
    "name": "Pavois gobelin",
    "result_item_code": "gobelin_warshield",
    "result_quantity": 1,
    "ingredients": [
      { "item_code": "gobelin_tooth", "quantity": 9 },
      { "item_code": "iron_ingot", "quantity": 3 },
      { "item_code": "wood_log", "quantity": 6 },
      { "item_code": "leather_strip", "quantity": 3 }
    ]
  },
  {
    "code": "leather_dagger_recipe",
    "name": "Dague en cuir",
    "result_item_code": "leather_dagger",
    "result_quantity": 1,
    "ingredients": [
      { "item_code": "leather_strip", "quantity": 2 },
      { "item_code": "wood_log", "quantity": 2 },
      { "item_code": "iron_ingot", "quantity": 1 }
    ]
  },
  {
    "code": "leather_buckler_recipe",
    "name": "Rondache en cuir",
    "result_item_code": "leather_buckler",
    "result_quantity": 1,
    "ingredients": [
      { "item_code": "leather_strip", "quantity": 2 },
      { "item_code": "wood_log", "quantity": 2 },
      { "item_code": "iron_ingot", "quantity": 1 }
    ]
  },
  {
    "code": "leather_greatsword_recipe",
    "name": "Grande lame en cuir",
    "result_item_code": "leather_greatsword",
    "result_quantity": 1,
    "ingredients": [
      { "item_code": "leather_strip", "quantity": 9 },
      { "item_code": "wood_log", "quantity": 6 },
      { "item_code": "iron_ingot", "quantity": 3 }
    ]
  },
  {
    "code": "leather_tower_shield_recipe",
    "name": "Tour en cuir",
    "result_item_code": "leather_tower_shield",
    "result_quantity": 1,
    "ingredients": [
      { "item_code": "leather_strip", "quantity": 9 },
      { "item_code": "wood_log", "quantity": 9 },
      { "item_code": "iron_ingot", "quantity": 3 }
    ]
  },
  {
    "code": "linen_rapier_recipe",
    "name": "Rapière en lin",
    "result_item_code": "linen_rapier",
    "result_quantity": 1,
    "ingredients": [
      { "item_code": "linen_cloth", "quantity": 2 },
      { "item_code": "wood_log", "quantity": 2 },
      { "item_code": "iron_ingot", "quantity": 1 }
    ]
  },
  {
    "code": "linen_aegis_recipe",
    "name": "Égide en lin",
    "result_item_code": "linen_aegis",
    "result_quantity": 1,
    "ingredients": [
      { "item_code": "linen_cloth", "quantity": 2 },
      { "item_code": "wood_log", "quantity": 2 },
      { "item_code": "leather_strip", "quantity": 1 }
    ]
  },
  {
    "code": "linen_greatblade_recipe",
    "name": "Grande lame en lin",
    "result_item_code": "linen_greatblade",
    "result_quantity": 1,
    "ingredients": [
      { "item_code": "linen_cloth", "quantity": 9 },
      { "item_code": "wood_log", "quantity": 6 },
      { "item_code": "iron_ingot", "quantity": 3 }
    ]
  },
  {
    "code": "linen_tower_shield_recipe",
    "name": "Tour en lin",
    "result_item_code": "linen_tower_shield",
    "result_quantity": 1,
    "ingredients": [
      { "item_code": "linen_cloth", "quantity": 9 },
      { "item_code": "wood_log", "quantity": 9 },
      { "item_code": "leather_strip", "quantity": 3 }
    ]
  }
]
