[
  {
    "code": "kill_slime_30",
    "name": "Chasse aux gélatines",
    "description": "Tuer 30 slimes durant la semaine.",
    "objective_type": "kill_family",
    "objective_target": "slime",
    "objective_quantity": 30,
    "reward_gold": 500,
    "reward_xp": 200,
    "reward_items": [["potion_soin_i", 3]],
    "tier": "easy"
  },
  {
    "code": "kill_slime_100",
    "name": "Slime Slayer en herbe",
    "description": "Tuer 100 slimes durant la semaine.",
    "objective_type": "kill_family",
    "objective_target": "slime",
    "objective_quantity": 100,
    "reward_gold": 1500,
    "reward_xp": 600,
    "reward_items": [["potion_soin_ii", 2]],
    "tier": "medium"
  },
  {
    "code": "kill_gobelin_30",
    "name": "Pacifier la horde",
    "description": "Tuer 30 gobelins durant la semaine.",
    "objective_type": "kill_family",
    "objective_target": "gobelin",
    "objective_quantity": 30,
    "reward_gold": 600,
    "reward_xp": 250,
    "reward_items": [["potion_soin_i", 3]],
    "tier": "easy"
  },
  {
    "code": "kill_gobelin_100",
    "name": "Bourreau gobelin",
    "description": "Tuer 100 gobelins durant la semaine.",
    "objective_type": "kill_family",
    "objective_target": "gobelin",
    "objective_quantity": 100,
    "reward_gold": 1800,
    "reward_xp": 700,
    "reward_items": [["potion_soin_ii", 2]],
    "tier": "medium"
  },
  {
    "code": "kill_total_50",
    "name": "Aventurier débutant",
    "description": "Tuer 50 monstres au total cette semaine.",
    "objective_type": "kill_total",
    "objective_target": "",
    "objective_quantity": 50,
    "reward_gold": 700,
    "reward_xp": 300,
    "reward_items": [["potion_soin_i", 5]],
    "tier": "easy"
  },
  {
    "code": "kill_total_200",
    "name": "Aventurier confirmé",
    "description": "Tuer 200 monstres au total cette semaine.",
    "objective_type": "kill_total",
    "objective_target": "",
    "objective_quantity": 200,
    "reward_gold": 3000,
    "reward_xp": 1200,
    "reward_items": [["potion_soin_iii", 2]],
    "tier": "hard"
  },
  {
    "code": "craft_5",
    "name": "Artisan du dimanche",
    "description": "Crafter 5 objets cette semaine (toutes recettes confondues).",
    "objective_type": "craft_any",
    "objective_target": "",
    "objective_quantity": 5,
    "reward_gold": 600,
    "reward_xp": 250,
    "reward_items": [["iron_ingot", 5]],
    "tier": "easy"
  },
  {
    "code": "craft_15",
    "name": "Artisan productif",
    "description": "Crafter 15 objets cette semaine.",
    "objective_type": "craft_any",
    "objective_target": "",
    "objective_quantity": 15,
    "reward_gold": 1800,
    "reward_xp": 750,
    "reward_items": [["leather_strip", 10], ["polished_stone", 5]],
    "tier": "medium"
  },
  {
    "code": "gather_20",
    "name": "Cueilleur attentif",
    "description": "Réussir 20 actions de récolte cette semaine.",
    "objective_type": "gather_count",
    "objective_target": "",
    "objective_quantity": 20,
    "reward_gold": 700,
    "reward_xp": 250,
    "reward_items": [["wood_log", 15]],
    "tier": "easy"
  },
  {
    "code": "gather_60",
    "name": "Récolteur acharné",
    "description": "Réussir 60 actions de récolte cette semaine.",
    "objective_type": "gather_count",
    "objective_target": "",
    "objective_quantity": 60,
    "reward_gold": 2200,
    "reward_xp": 850,
    "reward_items": [["polished_stone", 15], ["linen_cloth", 10]],
    "tier": "hard"
  },
  {
    "code": "gold_earned_2000",
    "name": "Mercenaire",
    "description": "Gagner 2 000 or via les combats cette semaine.",
    "objective_type": "gold_earned",
    "objective_target": "",
    "objective_quantity": 2000,
    "reward_gold": 1000,
    "reward_xp": 400,
    "reward_items": [["potion_soin_ii", 1]],
    "tier": "medium"
  },
  {
    "code": "gold_earned_10000",
    "name": "Petit fortuné",
    "description": "Gagner 10 000 or via les combats cette semaine.",
    "objective_type": "gold_earned",
    "objective_target": "",
    "objective_quantity": 10000,
    "reward_gold": 5000,
    "reward_xp": 2000,
    "reward_items": [["potion_soin_iii", 3]],
    "tier": "hard"
  },
  {
    "code": "boss_damage_50000",
    "name": "Frappeur de boss",
    "description": "Infliger 50 000 dégâts cumulés à un world boss cette semaine.",
    "objective_type": "boss_damage",
    "objective_target": "",
    "objective_quantity": 50000,
    "reward_gold": 1500,
    "reward_xp": 600,
    "reward_items": [["potion_soin_iii", 1]],
    "tier": "medium"
  },
  {
    "code": "boss_damage_500000",
    "name": "Briseur de boss",
    "description": "Infliger 500 000 dégâts cumulés à un world boss cette semaine.",
    "objective_type": "boss_damage",
    "objective_target": "",
    "objective_quantity": 500000,
    "reward_gold": 8000,
    "reward_xp": 3000,
    "reward_items": [["potion_soin_iii", 5]],
    "tier": "hard"
  },
  {
    "code": "daily_streak_5",
    "name": "Habitué",
    "description": "Atteindre 5 jours consécutifs de /daily cette semaine.",
    "objective_type": "daily_streak",
    "objective_target": "",
    "objective_quantity": 5,
    "reward_gold": 800,
    "reward_xp": 300,
    "reward_items": [["potion_soin_i", 5]],
    "tier": "easy"
  },
  {
    "code": "daily_streak_7",
    "name": "Régulier",
    "description": "Atteindre 7 jours consécutifs de /daily.",
    "objective_type": "daily_streak",
    "objective_target": "",
    "objective_quantity": 7,
    "reward_gold": 1500,
    "reward_xp": 600,
    "reward_items": [["potion_soin_ii", 3]],
    "tier": "medium"
  }
]
